energy_pinch/__init__.py
energy_pinch/__main__.py
energy_pinch/__version__.py
energy_pinch/module.py
Energy_Pinch-1.0.1.dist-info/LICENSE.txt
Energy_Pinch-1.0.1.dist-info/METADATA
Energy_Pinch-1.0.1.dist-info/WHEEL
Energy_Pinch-1.0.1.dist-info/top_level.txt
Energy_Pinch-1.0.1.dist-info/RECORD
